lakefs_sdk_async/__init__.py
lakefs_sdk_async/api/__init__.py
lakefs_sdk_async/api/actions_api.py
lakefs_sdk_async/api/auth_api.py
lakefs_sdk_async/api/branches_api.py
lakefs_sdk_async/api/commits_api.py
lakefs_sdk_async/api/config_api.py
lakefs_sdk_async/api/experimental_api.py
lakefs_sdk_async/api/external_api.py
lakefs_sdk_async/api/health_check_api.py
lakefs_sdk_async/api/import_api.py
lakefs_sdk_async/api/internal_api.py
lakefs_sdk_async/api/metadata_api.py
lakefs_sdk_async/api/objects_api.py
lakefs_sdk_async/api/pulls_api.py
lakefs_sdk_async/api/refs_api.py
lakefs_sdk_async/api/repositories_api.py
lakefs_sdk_async/api/staging_api.py
lakefs_sdk_async/api/tags_api.py
lakefs_sdk_async/api_client.py
lakefs_sdk_async/api_response.py
lakefs_sdk_async/client.py
lakefs_sdk_async/configuration.py
lakefs_sdk_async/exceptions.py
lakefs_sdk_async/models/__init__.py
lakefs_sdk_async/models/abort_presign_multipart_upload.py
lakefs_sdk_async/models/access_key_credentials.py
lakefs_sdk_async/models/acl.py
lakefs_sdk_async/models/action_run.py
lakefs_sdk_async/models/action_run_list.py
lakefs_sdk_async/models/auth_capabilities.py
lakefs_sdk_async/models/authentication_token.py
lakefs_sdk_async/models/branch_creation.py
lakefs_sdk_async/models/branch_protection_rule.py
lakefs_sdk_async/models/cherry_pick_creation.py
lakefs_sdk_async/models/comm_prefs_input.py
lakefs_sdk_async/models/commit.py
lakefs_sdk_async/models/commit_creation.py
lakefs_sdk_async/models/commit_list.py
lakefs_sdk_async/models/commit_overrides.py
lakefs_sdk_async/models/commit_record_creation.py
lakefs_sdk_async/models/complete_presign_multipart_upload.py
lakefs_sdk_async/models/config.py
lakefs_sdk_async/models/credentials.py
lakefs_sdk_async/models/credentials_list.py
lakefs_sdk_async/models/credentials_with_secret.py
lakefs_sdk_async/models/current_user.py
lakefs_sdk_async/models/diff.py
lakefs_sdk_async/models/diff_list.py
lakefs_sdk_async/models/error.py
lakefs_sdk_async/models/error_no_acl.py
lakefs_sdk_async-1.53.0.dist-info/METADATA
lakefs_sdk_async-1.53.0.dist-info/WHEEL
lakefs_sdk_async-1.53.0.dist-info/RECORD
