Metadata-Version: 2.1
Name: lakefs_sdk_async
Version: 1.53.0
Summary: lakeFS API
Home-page: https://github.com/treeverse/lakeFS
License: Apache 2.0
Keywords: OpenAPI,OpenAPI-Generator,lakeFS API
Author: Treeverse
Author-email: services@treeverse.io
Requires-Python: >=3.7,<4.0
Classifier: License :: Other/Proprietary License
Classifier: Programming Language :: Python :: 3
Classifier: Programming Language :: Python :: 3.7
Classifier: Programming Language :: Python :: 3.8
Classifier: Programming Language :: Python :: 3.9
Classifier: Programming Language :: Python :: 3.10
Classifier: Programming Language :: Python :: 3.11
Classifier: Programming Language :: Python :: 3.12
Classifier: Programming Language :: Python :: 3.13
Requires-Dist: aenum (>=3.1.11)
Requires-Dist: aiohttp (>=3.8.4)
Requires-Dist: pydantic (>=1.10.5)
Requires-Dist: python-dateutil (>=2.8.2)
Requires-Dist: urllib3 (>=1.25.3)
Project-URL: Repository, https://github.com/treeverse/lakeFS
